setup.py
pscc/__init__.py
pscc/config.py
pscc/items.py
pscc/parser.py
pscc/requests.py
pscc/selector.py
pscc/spider.py
pscc.egg-info/PKG-INFO
pscc.egg-info/SOURCES.txt
pscc.egg-info/dependency_links.txt
pscc.egg-info/not-zip-safe
pscc.egg-info/requires.txt
pscc.egg-info/top_level.txt
pscc/decorator/__init__.py
pscc/decorator/logger.py
pscc/decorator/runtime.py
pscc/middle_ware/__init__.py
pscc/store/__init__.py
pscc/store/aio_db/__init__.py
pscc/store/aio_db/control.py
pscc/store/aio_file/__init__.py
pscc/store/aio_file/control.py
pscc/store/aio_redis/__init__.py
pscc/utils/Error.py
pscc/utils/Logconfig.py
pscc/utils/Mail.py
pscc/utils/__init__.py
pscc/utils/bloom_filter.py
test/__init__.py
test/api_test.py
test/base_test.py
test/base_test_1.py
test/file_test.py
test/mysql_test.py
test/test_item.py