Metadata-Version: 1.0
Name: pscc
Version: 0.1.0
Summary: Crawler Everything For You By Anyone.
Home-page: https://github.com/PythonScientists/Pscc
Author: PSC
Author-email: pythonscientists@outlook.com
License: GNU GPL 3
Platform: UNKNOWN
